pyscenic/__init__.py
pyscenic/_version.py
pyscenic/aucell.py
pyscenic/binarization.py
pyscenic/diptest.py
pyscenic/export.py
pyscenic/featureseq.py
pyscenic/log.py
pyscenic/math.py
pyscenic/plotting.py
pyscenic/prune.py
pyscenic/rss.py
pyscenic/transform.py
pyscenic/utils.py
pyscenic/cli/__init__.py
pyscenic/cli/arboreto_with_multiprocessing.py
pyscenic/cli/csv2loom.py
pyscenic/cli/pyscenic.py
pyscenic/cli/utils.py
pyscenic-0.12.1.data/scripts/arboreto_with_multiprocessing.py
resources/__init__.py
resources/scenic.args.txt
resources/delineations/__init__.py
resources/tests/GSE103322.em.hgnc.sample.cxg.csv
resources/tests/__init__.py
resources/tests/c6.all.v6.1.symbols.gmt
resources/tests/hg19-tss-centered-10kb-10species.mc9nr.feather
resources/tests/hg19-tss-centered-5kb-10species.mc9nr.db
pyscenic-0.12.1.dist-info/LICENSE.txt
pyscenic-0.12.1.dist-info/METADATA
pyscenic-0.12.1.dist-info/WHEEL
pyscenic-0.12.1.dist-info/entry_points.txt
pyscenic-0.12.1.dist-info/top_level.txt
pyscenic-0.12.1.dist-info/RECORD
