Metadata-Version: 2.1
Name: pyscenic
Version: 0.12.1
Summary: Python implementation of the SCENIC pipeline for transcription factor inference from single-cell transcriptomics experiments.
Home-page: https://github.com/aertslab/pySCENIC
Author: Bram Van de Sande
License: GPL-3.0+
Keywords: single-cell transcriptomics gene-regulatory-network transcription-factors
Platform: UNKNOWN
Classifier: Development Status :: 4 - Beta
Classifier: License :: OSI Approved :: GNU General Public License v3 or later (GPLv3+)
Classifier: Natural Language :: English
Classifier: Operating System :: POSIX
Classifier: Programming Language :: Python
Classifier: Programming Language :: Python :: 3
Classifier: Programming Language :: Python :: 3.5
Classifier: Programming Language :: Python :: 3.6
Classifier: Programming Language :: Python :: Implementation :: CPython
Requires-Python: >=3.6
Requires-Dist: ctxcore (>=0.2.0)
Requires-Dist: cytoolz
Requires-Dist: multiprocessing-on-dill
Requires-Dist: llvmlite
Requires-Dist: numba (>=0.51.2)
Requires-Dist: attrs
Requires-Dist: frozendict
Requires-Dist: numpy
Requires-Dist: pandas (>=1.3.5)
Requires-Dist: numexpr
Requires-Dist: cloudpickle
Requires-Dist: dask
Requires-Dist: distributed
Requires-Dist: arboreto (>=0.1.6)
Requires-Dist: boltons
Requires-Dist: setuptools
Requires-Dist: pyyaml
Requires-Dist: tqdm
Requires-Dist: interlap
Requires-Dist: umap-learn
Requires-Dist: loompy
Requires-Dist: networkx
Requires-Dist: scipy
Requires-Dist: fsspec
Requires-Dist: requests
Requires-Dist: aiohttp
Requires-Dist: scikit-learn (>=0.22.2)
